hydrodatasource/__init__.py
hydrodatasource/_version.py
hydrodatasource/cleaner/__init__.py
hydrodatasource/cleaner/cleaner.py
hydrodatasource/cleaner/rainfall_cleaner.py
hydrodatasource/cleaner/rsvr_inflow_cleaner.py
hydrodatasource/cleaner/streamflow_cleaner.py
hydrodatasource/cleaner/waterlevel_cleaner.py
hydrodatasource/configs/__init__.py
hydrodatasource/configs/config.py
hydrodatasource/configs/data_consts.py
hydrodatasource/configs/table_name.py
hydrodatasource/processor/__init__.py
hydrodatasource/processor/basin_mean_rainfall.py
hydrodatasource/processor/dmca_esr.py
hydrodatasource/reader/__init__.py
hydrodatasource/reader/access_fs.py
hydrodatasource/reader/data_source.py
hydrodatasource/reader/floodevent.py
hydrodatasource/reader/gages.py
hydrodatasource/reader/grdc.py
hydrodatasource/reader/minio_api.py
hydrodatasource/reader/rainfall_reader.py
hydrodatasource/reader/reservoir_datasets.py
hydrodatasource/reader/rsvr_inflow_reader.py
hydrodatasource/utils/__init__.py
hydrodatasource/utils/utils.py
hydrodatasource-0.2.0.dist-info/METADATA
hydrodatasource-0.2.0.dist-info/WHEEL
hydrodatasource-0.2.0.dist-info/licenses/AUTHORS.rst
hydrodatasource-0.2.0.dist-info/licenses/LICENSE
hydrodatasource-0.2.0.dist-info/RECORD
