Metadata-Version: 2.4
Name: hydrodatasource
Version: 0.2.0
Summary: A python project to deal with hydrological datasources
Project-URL: Homepage, https://github.com/iHeadWater/hydrodatasource
Project-URL: Repository, https://github.com/iHeadWater/hydrodatasource
Project-URL: Documentation, https://github.com/iHeadWater/hydrodatasource
Project-URL: Bug Tracker, https://github.com/iHeadWater/hydrodatasource/issues
Author-email: Wenyu Ouyang <hust2014owen@gmail.com>
License: BSD License
License-File: AUTHORS.rst
License-File: LICENSE
Keywords: data,geospatial,hydrodatasource,hydrology,water
Classifier: Intended Audience :: Developers
Classifier: License :: OSI Approved :: BSD License
Classifier: Natural Language :: English
Classifier: Programming Language :: Python :: 3
Classifier: Programming Language :: Python :: 3.10
Classifier: Programming Language :: Python :: 3.11
Classifier: Programming Language :: Python :: 3.12
Requires-Python: >=3.10
Requires-Dist: aqua-fetch[all]
Requires-Dist: cfgrib
Requires-Dist: chardet
Requires-Dist: dataretrieval
Requires-Dist: eccodes
Requires-Dist: geopandas
Requires-Dist: h5py
Requires-Dist: hydrodataset>=0.2.0
Requires-Dist: hydrotopo
Requires-Dist: hydroutils>=0.1.0
Requires-Dist: intake
Requires-Dist: kerchunk
Requires-Dist: loguru
Requires-Dist: openpyxl
Requires-Dist: polars
Requires-Dist: psycopg2-binary
Requires-Dist: pygeohydro
Requires-Dist: pykalman
Requires-Dist: pywavelets
Requires-Dist: requests
Requires-Dist: scipy
Requires-Dist: sqlalchemy
Requires-Dist: wget
Requires-Dist: xarray
Requires-Dist: xlrd
Provides-Extra: dev
Requires-Dist: black; extra == 'dev'
Requires-Dist: black[jupyter]; extra == 'dev'
Requires-Dist: coverage; extra == 'dev'
Requires-Dist: flake8; extra == 'dev'
Requires-Dist: pytest; extra == 'dev'
Requires-Dist: pytest-asyncio; extra == 'dev'
Requires-Dist: pytest-mock; extra == 'dev'
Requires-Dist: pytest-runner; extra == 'dev'
Requires-Dist: tox; extra == 'dev'
Requires-Dist: twine; extra == 'dev'
Requires-Dist: watchdog; extra == 'dev'
Requires-Dist: wheel; extra == 'dev'
Provides-Extra: docs
Requires-Dist: ipykernel; extra == 'docs'
Requires-Dist: livereload; extra == 'docs'
Requires-Dist: mkdocs; extra == 'docs'
Requires-Dist: mkdocs-git-revision-date-localized-plugin; extra == 'docs'
Requires-Dist: mkdocs-git-revision-date-plugin; extra == 'docs'
Requires-Dist: mkdocs-include-markdown-plugin; extra == 'docs'
Requires-Dist: mkdocs-jupyter>=0.24.0; extra == 'docs'
Requires-Dist: mkdocs-material>=9.1.3; extra == 'docs'
Requires-Dist: mkdocs-pdf-export-plugin; extra == 'docs'
Requires-Dist: mkdocstrings; extra == 'docs'
Requires-Dist: mkdocstrings-crystal; extra == 'docs'
Requires-Dist: mkdocstrings-python-legacy; extra == 'docs'
Requires-Dist: nbconvert; extra == 'docs'
Requires-Dist: nbformat; extra == 'docs'
Requires-Dist: pygments; extra == 'docs'
Requires-Dist: pymdown-extensions; extra == 'docs'
Requires-Dist: sphinx; extra == 'docs'
